rdl2ot/__init__.py
rdl2ot/__main__.py
rdl2ot/__peakrdl__.py
rdl2ot/cli.py
rdl2ot/opentitan.py
rdl2ot/rtl_exporter.py
templates/qemu_ip.c.tpl
templates/reg_pkg.sv.tpl
templates/reg_top.sv.tpl
rdl2ot-0.4.0.dist-info/METADATA
rdl2ot-0.4.0.dist-info/WHEEL
rdl2ot-0.4.0.dist-info/entry_points.txt
rdl2ot-0.4.0.dist-info/RECORD
