Metadata-Version: 2.4
Name: rdl2ot
Version: 0.4.0
Summary: An extension of PeakRDL to generate OpenTitan RTL.
Project-URL: Homepage, https://github.com/lowrisc/benevisrdl
Project-URL: Issues, https://github.com/lowrisc/benevisrdl/issues
Project-URL: Documentation, https://github.com/lowrisc/benevisrdl
Author: lowRISC contributors
Keywords: Codegen,OpenTitan,SystemRDL
Requires-Python: >=3.10
Requires-Dist: click>=8.3.0
Requires-Dist: jinja2>=3.1.6
Requires-Dist: systemrdl-compiler~=1.32.1
